Metadata-Version: 1.0
Name: binomial-package-Scripts
Version: 1.0
Summary: Gaussian and Binomial distributions
Home-page: UNKNOWN
Author: Andre Muth
Author-email: andremuth@gmx.de
License: UNKNOWN
Platform: UNKNOWN
